eggeR/__init__.py
eggeR/client.py
eggerblx-0.1.1.dist-info/licenses/LICENSE.md
eggerblx-0.1.1.dist-info/METADATA
eggerblx-0.1.1.dist-info/WHEEL
eggerblx-0.1.1.dist-info/top_level.txt
eggerblx-0.1.1.dist-info/RECORD
