Metadata-Version: 2.4
Name: eggeRblx
Version: 0.1.1
Summary: Roblox Users API wrapper
Author: egge
Author-email: tspmoegge@gmail.com
License: MIT
Requires-Python: >=3.8
License-File: LICENSE.md
Requires-Dist: requests
Dynamic: author
Dynamic: author-email
Dynamic: description
Dynamic: description-content-type
Dynamic: license
Dynamic: license-file
Dynamic: requires-dist
Dynamic: requires-python
Dynamic: summary
